swaystatus/__init__.py
swaystatus/__main__.py
swaystatus/app.py
swaystatus/block.py
swaystatus/cli.py
swaystatus/click_event.py
swaystatus/config.py
swaystatus/daemon.py
swaystatus/element.py
swaystatus/env.py
swaystatus/input.py
swaystatus/logging.py
swaystatus/modules.py
swaystatus/output.py
swaystatus/py.typed
swaystatus/subprocess.py
swaystatus/threading.py
swaystatus/version
swaystatus/version.py
swaystatus/xdg.py
swaystatus-0.11.1.dist-info/licenses/LICENSE
swaystatus-0.11.1.dist-info/WHEEL
swaystatus-0.11.1.dist-info/entry_points.txt
swaystatus-0.11.1.dist-info/METADATA
swaystatus-0.11.1.dist-info/RECORD
