Metadata-Version: 2.4
Name: swaystatus
Version: 0.11.1
Summary: Generate a status line for swaybar
Keywords: sway,wm,status
Author: Jeremy Cantrell
Author-email: Jeremy Cantrell <jmcantrell@gmail.com>
License-File: LICENSE
Classifier: Development Status :: 4 - Beta
Classifier: Environment :: Console
Classifier: Intended Audience :: Developers
Classifier: Intended Audience :: End Users/Desktop
Classifier: Intended Audience :: System Administrators
Classifier: License :: OSI Approved :: MIT License
Classifier: Operating System :: POSIX :: Linux
Classifier: Programming Language :: Python :: 3 :: Only
Classifier: Programming Language :: Python :: 3
Classifier: Programming Language :: Python :: 3.12
Classifier: Topic :: Desktop Environment :: Window Managers
Classifier: Topic :: Desktop Environment
Classifier: Typing :: Typed
Requires-Python: >=3.14
Project-URL: Bug Tracker, https://todo.sr.ht/~jmcantrell/swaystatus
Project-URL: Homepage, https://sr.ht/~jmcantrell/swaystatus/
Project-URL: Repository, https://git.sr.ht/~jmcantrell/swaystatus
